change_case/__init__.py
change_case/no_case.py
changecase-0.0.2.dist-info/WHEEL
changecase-0.0.2.dist-info/METADATA
changecase-0.0.2.dist-info/RECORD
