Metadata-Version: 1.2
Name: changecase
Version: 0.0.2
Summary: Change case of strings. More documentation to come.
Home-page: https://github.com/thrawny/change-case
License: UNKNOWN
Author: Jonas Lergell
Author-email: jonaslergell@gmail.com
Classifier: License :: OSI Approved :: MIT License
